<?xml version="1.0" encoding="utf-8"?>
<LipSyncVisemes wavFile="TTS-3256FC2D61353D3C62523656D7801263.wav">
  <viseme type="19" time="0.085" duration="0.07" />
  <viseme type="8" time="0.155" duration="0.175" />
  <viseme type="2" time="1.085" duration="0.055" />
  <viseme type="6" time="1.14" duration="0.055" />
  <viseme type="7" time="1.195" duration="0.045" />
  <viseme type="6" time="1.24" duration="0.04" />
  <viseme type="14" time="1.28" duration="0.06" />
  <viseme type="1" time="1.34" duration="0.105" />
  <viseme type="19" time="1.445" duration="0.04" />
  <viseme type="15" time="1.485" duration="0.07" />
  <viseme type="1" time="1.555" duration="0.04" />
  <viseme type="13" time="1.595" duration="0.04" />
  <viseme type="17" time="1.635" duration="0.04" />
  <viseme type="1" time="1.675" duration="0.04" />
  <viseme type="20" time="1.715" duration="0.075" />
  <viseme type="7" time="1.79" duration="0.045" />
  <viseme type="4" time="1.835" duration="0.07" />
  <viseme type="15" time="1.905" duration="0.075" />
  <viseme type="19" time="1.98" duration="0.03" />
  <viseme type="16" time="2.01" duration="0.03" />
  <viseme type="1" time="2.04" duration="0.07" />
  <viseme type="19" time="2.11" duration="0.075" />
  <viseme type="15" time="2.185" duration="0.16" />
</LipSyncVisemes>